{
  "file_to_generate": [
    "internal/proto/messages.proto"
  ],
  "proto_file": [
    {
      "name": "internal/proto/messages.proto",
      "message_type": [
        {
          "name": "Packet",
          "field": [
            {
              "name": "event",
              "number": 1,
              "label": 1,
              "type": 14,
              "type_name": ".EventType",
              "json_name": "event"
            },
            {
              "name": "sit",
              "number": 2,
              "label": 1,
              "type": 11,
              "type_name": ".SitEvent",
              "oneof_index": 0,
              "json_name": "sit"
            },
            {
              "name": "stand",
              "number": 3,
              "label": 1,
              "type": 11,
              "type_name": ".StandEvent",
              "oneof_index": 0,
              "json_name": "stand"
            },
            {
              "name": "sit_ack",
              "number": 4,
              "label": 1,
              "type": 11,
              "type_name": ".SitAck",
              "oneof_index": 0,
              "json_name": "sitAck"
            },
            {
              "name": "stand_ack",
              "number": 5,
              "label": 1,
              "type": 11,
              "type_name": ".StandAck",
              "oneof_index": 0,
              "json_name": "standAck"
            },
            {
              "name": "join_state",
              "number": 6,
              "label": 1,
              "type": 11,
              "type_name": ".TableState",
              "oneof_index": 0,
              "json_name": "joinState"
            },
            {
              "name": "hand",
              "number": 7,
              "label": 1,
              "type": 11,
              "type_name": ".CardSet",
              "oneof_index": 0,
              "json_name": "hand"
            },
            {
              "name": "flop",
              "number": 8,
              "label": 1,
              "type": 11,
              "type_name": ".CardSet",
              "oneof_index": 0,
              "json_name": "flop"
            },
            {
              "name": "turn",
              "number": 9,
              "label": 1,
              "type": 11,
              "type_name": ".CardSet",
              "oneof_index": 0,
              "json_name": "turn"
            },
            {
              "name": "river",
              "number": 10,
              "label": 1,
              "type": 11,
              "type_name": ".CardSet",
              "oneof_index": 0,
              "json_name": "river"
            },
            {
              "name": "action",
              "number": 11,
              "label": 1,
              "type": 11,
              "type_name": ".ActionMsg",
              "oneof_index": 0,
              "json_name": "action"
            },
            {
              "name": "action_ack",
              "number": 12,
              "label": 1,
              "type": 11,
              "type_name": ".ActionAck",
              "oneof_index": 0,
              "json_name": "actionAck"
            },
            {
              "name": "msg_send",
              "number": 100,
              "label": 1,
              "type": 11,
              "type_name": ".ChatMsgSend",
              "oneof_index": 0,
              "json_name": "msgSend"
            },
            {
              "name": "msg_recv",
              "number": 101,
              "label": 1,
              "type": 11,
              "type_name": ".ChatMsgRecv",
              "oneof_index": 0,
              "json_name": "msgRecv"
            }
          ],
          "oneof_decl": [
            {
              "name": "payload"
            }
          ]
        },
        {
          "name": "SitEvent",
          "field": [
            {
              "name": "table_id",
              "number": 1,
              "label": 1,
              "type": 9,
              "json_name": "tableId"
            },
            {
              "name": "user_identity_token",
              "number": 2,
              "label": 1,
              "type": 9,
              "json_name": "userIdentityToken"
            },
            {
              "name": "chips",
              "number": 3,
              "label": 1,
              "type": 5,
              "json_name": "chips"
            }
          ]
        },
        {
          "name": "StandEvent",
          "field": [
            {
              "name": "table_id",
              "number": 1,
              "label": 1,
              "type": 9,
              "json_name": "tableId"
            }
          ]
        },
        {
          "name": "SitAck",
          "field": [
            {
              "name": "table_id",
              "number": 1,
              "label": 1,
              "type": 9,
              "json_name": "tableId"
            },
            {
              "name": "sat_down",
              "number": 2,
              "label": 1,
              "type": 8,
              "json_name": "satDown"
            },
            {
              "name": "seat_num",
              "number": 3,
              "label": 1,
              "type": 5,
              "json_name": "seatNum"
            },
            {
              "name": "reason",
              "number": 4,
              "label": 1,
              "type": 9,
              "json_name": "reason"
            }
          ]
        },
        {
          "name": "StandAck",
          "field": [
            {
              "name": "table_id",
              "number": 1,
              "label": 1,
              "type": 9,
              "json_name": "tableId"
            },
            {
              "name": "stood_up",
              "number": 2,
              "label": 1,
              "type": 8,
              "json_name": "stoodUp"
            },
            {
              "name": "balance",
              "number": 3,
              "label": 1,
              "type": 5,
              "json_name": "balance"
            },
            {
              "name": "reason",
              "number": 4,
              "label": 1,
              "type": 9,
              "json_name": "reason"
            }
          ]
        },
        {
          "name": "TableState",
          "field": [
            {
              "name": "table_id",
              "number": 1,
              "label": 1,
              "type": 9,
              "json_name": "tableId"
            },
            {
              "name": "min_buy",
              "number": 2,
              "label": 1,
              "type": 5,
              "json_name": "minBuy"
            },
            {
              "name": "max_seats",
              "number": 3,
              "label": 1,
              "type": 5,
              "json_name": "maxSeats"
            },
            {
              "name": "big_blind",
              "number": 4,
              "label": 1,
              "type": 5,
              "json_name": "bigBlind"
            },
            {
              "name": "seats",
              "number": 5,
              "label": 3,
              "type": 11,
              "type_name": ".PlayerSeat",
              "json_name": "seats"
            }
          ]
        },
        {
          "name": "PlayerSeat",
          "field": [
            {
              "name": "player",
              "number": 1,
              "label": 1,
              "type": 9,
              "json_name": "player"
            },
            {
              "name": "balance",
              "number": 2,
              "label": 1,
              "type": 5,
              "json_name": "balance"
            },
            {
              "name": "seat_num",
              "number": 3,
              "label": 1,
              "type": 5,
              "json_name": "seatNum"
            }
          ]
        },
        {
          "name": "Card",
          "field": [
            {
              "name": "suit",
              "number": 1,
              "label": 1,
              "type": 5,
              "json_name": "suit"
            },
            {
              "name": "rank",
              "number": 2,
              "label": 1,
              "type": 5,
              "json_name": "rank"
            },
            {
              "name": "display",
              "number": 3,
              "label": 1,
              "type": 9,
              "json_name": "display"
            }
          ]
        },
        {
          "name": "CardSet",
          "field": [
            {
              "name": "cards",
              "number": 1,
              "label": 3,
              "type": 11,
              "type_name": ".Card",
              "json_name": "cards"
            }
          ]
        },
        {
          "name": "ChatMsgSend",
          "field": [
            {
              "name": "data",
              "number": 1,
              "label": 1,
              "type": 9,
              "json_name": "data"
            }
          ]
        },
        {
          "name": "ChatMsgRecv",
          "field": [
            {
              "name": "message_id",
              "number": 1,
              "label": 1,
              "type": 5,
              "json_name": "messageId"
            },
            {
              "name": "player_id",
              "number": 2,
              "label": 1,
              "type": 9,
              "json_name": "playerId"
            },
            {
              "name": "data",
              "number": 3,
              "label": 1,
              "type": 9,
              "json_name": "data"
            },
            {
              "name": "timestamp",
              "number": 4,
              "label": 1,
              "type": 5,
              "json_name": "timestamp"
            }
          ]
        },
        {
          "name": "ActionMsg",
          "field": [
            {
              "name": "type",
              "number": 1,
              "label": 1,
              "type": 14,
              "type_name": ".ActionType",
              "json_name": "type"
            },
            {
              "name": "chips",
              "number": 2,
              "label": 1,
              "type": 5,
              "json_name": "chips"
            },
            {
              "name": "nonce",
              "number": 3,
              "label": 1,
              "type": 5,
              "json_name": "nonce"
            }
          ]
        },
        {
          "name": "ActionAck",
          "field": [
            {
              "name": "ok",
              "number": 1,
              "label": 1,
              "type": 8,
              "json_name": "ok"
            },
            {
              "name": "error",
              "number": 2,
              "label": 1,
              "type": 9,
              "json_name": "error"
            },
            {
              "name": "nonce",
              "number": 3,
              "label": 1,
              "type": 5,
              "json_name": "nonce"
            }
          ]
        }
      ],
      "enum_type": [
        {
          "name": "EventType",
          "value": [
            {
              "name": "UNDEFINED",
              "number": 0
            },
            {
              "name": "JOIN_ROOM",
              "number": 32
            },
            {
              "name": "TABLE_STATE",
              "number": 33
            },
            {
              "name": "TABLE_SIT",
              "number": 34
            },
            {
              "name": "TABLE_STAND",
              "number": 35
            },
            {
              "name": "TABLE_SIT_ACK",
              "number": 36
            },
            {
              "name": "TABLE_STAND_ACK",
              "number": 37
            },
            {
              "name": "HAND",
              "number": 51
            },
            {
              "name": "FLOP",
              "number": 52
            },
            {
              "name": "TURN",
              "number": 53
            },
            {
              "name": "RIVER",
              "number": 54
            },
            {
              "name": "TIMER",
              "number": 64
            },
            {
              "name": "ACTION",
              "number": 65
            },
            {
              "name": "ACTION_ACK",
              "number": 66
            },
            {
              "name": "CHAT_MSG_SEND",
              "number": 128
            },
            {
              "name": "CHAT_MSG_RECV",
              "number": 129
            }
          ]
        },
        {
          "name": "ActionType",
          "value": [
            {
              "name": "UNKNOWN",
              "number": 0
            },
            {
              "name": "CHECK",
              "number": 1
            },
            {
              "name": "CALL",
              "number": 2
            },
            {
              "name": "BET",
              "number": 3
            },
            {
              "name": "RAISE",
              "number": 4
            },
            {
              "name": "ALL_IN",
              "number": 5
            }
          ]
        }
      ],
      "source_code_info": {
        "location": [
          {
            "span": [
              7,
              0,
              138,
              1
            ]
          },
          {
            "path": [
              12
            ],
            "span": [
              7,
              0,
              18
            ],
            "leading_detached_comments": [
              "*\n @exclude\n Please ensure comments are updated when fields are updated\n comments are used to generate documentation via protoc-gen-go\n"
            ]
          },
          {
            "path": [
              5,
              0
            ],
            "span": [
              9,
              0,
              32,
              1
            ]
          },
          {
            "path": [
              5,
              0,
              1
            ],
            "span": [
              9,
              5,
              14
            ]
          },
          {
            "path": [
              5,
              0,
              2,
              0
            ],
            "span": [
              10,
              4,
              18
            ]
          },
          {
            "path": [
              5,
              0,
              2,
              0,
              1
            ],
            "span": [
              10,
              4,
              13
            ]
          },
          {
            "path": [
              5,
              0,
              2,
              0,
              2
            ],
            "span": [
              10,
              16,
              17
            ]
          },
          {
            "path": [
              5,
              0,
              2,
              1
            ],
            "span": [
              13,
              4,
              19
            ],
            "leading_comments": " Event used when we're join the room, for chat messages\n"
          },
          {
            "path": [
              5,
              0,
              2,
              1,
              1
            ],
            "span": [
              13,
              4,
              13
            ]
          },
          {
            "path": [
              5,
              0,
              2,
              1,
              2
            ],
            "span": [
              13,
              16,
              18
            ]
          },
          {
            "path": [
              5,
              0,
              2,
              2
            ],
            "span": [
              14,
              4,
              21
            ]
          },
          {
            "path": [
              5,
              0,
              2,
              2,
              1
            ],
            "span": [
              14,
              4,
              15
            ]
          },
          {
            "path": [
              5,
              0,
              2,
              2,
              2
            ],
            "span": [
              14,
              18,
              20
            ]
          },
          {
            "path": [
              5,
              0,
              2,
              3
            ],
            "span": [
              15,
              4,
              19
            ]
          },
          {
            "path": [
              5,
              0,
              2,
              3,
              1
            ],
            "span": [
              15,
              4,
              13
            ]
          },
          {
            "path": [
              5,
              0,
              2,
              3,
              2
            ],
            "span": [
              15,
              16,
              18
            ]
          },
          {
            "path": [
              5,
              0,
              2,
              4
            ],
            "span": [
              16,
              4,
              21
            ]
          },
          {
            "path": [
              5,
              0,
              2,
              4,
              1
            ],
            "span": [
              16,
              4,
              15
            ]
          },
          {
            "path": [
              5,
              0,
              2,
              4,
              2
            ],
            "span": [
              16,
              18,
              20
            ]
          },
          {
            "path": [
              5,
              0,
              2,
              5
            ],
            "span": [
              18,
              4,
              23
            ]
          },
          {
            "path": [
              5,
              0,
              2,
              5,
              1
            ],
            "span": [
              18,
              4,
              17
            ]
          },
          {
            "path": [
              5,
              0,
              2,
              5,
              2
            ],
            "span": [
              18,
              20,
              22
            ]
          },
          {
            "path": [
              5,
              0,
              2,
              6
            ],
            "span": [
              19,
              4,
              25
            ]
          },
          {
            "path": [
              5,
              0,
              2,
              6,
              1
            ],
            "span": [
              19,
              4,
              19
            ]
          },
          {
            "path": [
              5,
              0,
              2,
              6,
              2
            ],
            "span": [
              19,
              22,
              24
            ]
          },
          {
            "path": [
              5,
              0,
              2,
              7
            ],
            "span": [
              21,
              4,
              14
            ]
          },
          {
            "path": [
              5,
              0,
              2,
              7,
              1
            ],
            "span": [
              21,
              4,
              8
            ]
          },
          {
            "path": [
              5,
              0,
              2,
              7,
              2
            ],
            "span": [
              21,
              11,
              13
            ]
          },
          {
            "path": [
              5,
              0,
              2,
              8
            ],
            "span": [
              22,
              4,
              14
            ]
          },
          {
            "path": [
              5,
              0,
              2,
              8,
              1
            ],
            "span": [
              22,
              4,
              8
            ]
          },
          {
            "path": [
              5,
              0,
              2,
              8,
              2
            ],
            "span": [
              22,
              11,
              13
            ]
          },
          {
            "path": [
              5,
              0,
              2,
              9
            ],
            "span": [
              23,
              4,
              14
            ]
          },
          {
            "path": [
              5,
              0,
              2,
              9,
              1
            ],
            "span": [
              23,
              4,
              8
            ]
          },
          {
            "path": [
              5,
              0,
              2,
              9,
              2
            ],
            "span": [
              23,
              11,
              13
            ]
          },
          {
            "path": [
              5,
              0,
              2,
              10
            ],
            "span": [
              24,
              4,
              15
            ]
          },
          {
            "path": [
              5,
              0,
              2,
              10,
              1
            ],
            "span": [
              24,
              4,
              9
            ]
          },
          {
            "path": [
              5,
              0,
              2,
              10,
              2
            ],
            "span": [
              24,
              12,
              14
            ]
          },
          {
            "path": [
              5,
              0,
              2,
              11
            ],
            "span": [
              26,
              4,
              15
            ]
          },
          {
            "path": [
              5,
              0,
              2,
              11,
              1
            ],
            "span": [
              26,
              4,
              9
            ]
          },
          {
            "path": [
              5,
              0,
              2,
              11,
              2
            ],
            "span": [
              26,
              12,
              14
            ]
          },
          {
            "path": [
              5,
              0,
              2,
              12
            ],
            "span": [
              27,
              4,
              16
            ]
          },
          {
            "path": [
              5,
              0,
              2,
              12,
              1
            ],
            "span": [
              27,
              4,
              10
            ]
          },
          {
            "path": [
              5,
              0,
              2,
              12,
              2
            ],
            "span": [
              27,
              13,
              15
            ]
          },
          {
            "path": [
              5,
              0,
              2,
              13
            ],
            "span": [
              28,
              4,
              20
            ]
          },
          {
            "path": [
              5,
              0,
              2,
              13,
              1
            ],
            "span": [
              28,
              4,
              14
            ]
          },
          {
            "path": [
              5,
              0,
              2,
              13,
              2
            ],
            "span": [
              28,
              17,
              19
            ]
          },
          {
            "path": [
              5,
              0,
              2,
              14
            ],
            "span": [
              30,
              4,
              24
            ]
          },
          {
            "path": [
              5,
              0,
              2,
              14,
              1
            ],
            "span": [
              30,
              4,
              17
            ]
          },
          {
            "path": [
              5,
              0,
              2,
              14,
              2
            ],
            "span": [
              30,
              20,
              23
            ]
          },
          {
            "path": [
              5,
              0,
              2,
              15
            ],
            "span": [
              31,
              4,
              24
            ]
          },
          {
            "path": [
              5,
              0,
              2,
              15,
              1
            ],
            "span": [
              31,
              4,
              17
            ]
          },
          {
            "path": [
              5,
              0,
              2,
              15,
              2
            ],
            "span": [
              31,
              20,
              23
            ]
          },
          {
            "path": [
              4,
              0
            ],
            "span": [
              34,
              0,
              56,
              1
            ]
          },
          {
            "path": [
              4,
              0,
              1
            ],
            "span": [
              34,
              8,
              14
            ]
          },
          {
            "path": [
              4,
              0,
              2,
              0
            ],
            "span": [
              35,
              4,
              24
            ]
          },
          {
            "path": [
              4,
              0,
              2,
              0,
              6
            ],
            "span": [
              35,
              4,
              13
            ]
          },
          {
            "path": [
              4,
              0,
              2,
              0,
              1
            ],
            "span": [
              35,
              14,
              19
            ]
          },
          {
            "path": [
              4,
              0,
              2,
              0,
              3
            ],
            "span": [
              35,
              22,
              23
            ]
          },
          {
            "path": [
              4,
              0,
              8,
              0
            ],
            "span": [
              36,
              4,
              55,
              5
            ]
          },
          {
            "path": [
              4,
              0,
              8,
              0,
              1
            ],
            "span": [
              36,
              10,
              17
            ]
          },
          {
            "path": [
              4,
              0,
              2,
              1
            ],
            "span": [
              37,
              8,
              25
            ]
          },
          {
            "path": [
              4,
              0,
              2,
              1,
              6
            ],
            "span": [
              37,
              8,
              16
            ]
          },
          {
            "path": [
              4,
              0,
              2,
              1,
              1
            ],
            "span": [
              37,
              17,
              20
            ]
          },
          {
            "path": [
              4,
              0,
              2,
              1,
              3
            ],
            "span": [
              37,
              23,
              24
            ]
          },
          {
            "path": [
              4,
              0,
              2,
              2
            ],
            "span": [
              38,
              8,
              29
            ]
          },
          {
            "path": [
              4,
              0,
              2,
              2,
              6
            ],
            "span": [
              38,
              8,
              18
            ]
          },
          {
            "path": [
              4,
              0,
              2,
              2,
              1
            ],
            "span": [
              38,
              19,
              24
            ]
          },
          {
            "path": [
              4,
              0,
              2,
              2,
              3
            ],
            "span": [
              38,
              27,
              28
            ]
          },
          {
            "path": [
              4,
              0,
              2,
              3
            ],
            "span": [
              40,
              8,
              27
            ]
          },
          {
            "path": [
              4,
              0,
              2,
              3,
              6
            ],
            "span": [
              40,
              8,
              14
            ]
          },
          {
            "path": [
              4,
              0,
              2,
              3,
              1
            ],
            "span": [
              40,
              15,
              22
            ]
          },
          {
            "path": [
              4,
              0,
              2,
              3,
              3
            ],
            "span": [
              40,
              25,
              26
            ]
          },
          {
            "path": [
              4,
              0,
              2,
              4
            ],
            "span": [
              41,
              8,
              31
            ]
          },
          {
            "path": [
              4,
              0,
              2,
              4,
              6
            ],
            "span": [
              41,
              8,
              16
            ]
          },
          {
            "path": [
              4,
              0,
              2,
              4,
              1
            ],
            "span": [
              41,
              17,
              26
            ]
          },
          {
            "path": [
              4,
              0,
              2,
              4,
              3
            ],
            "span": [
              41,
              29,
              30
            ]
          },
          {
            "path": [
              4,
              0,
              2,
              5
            ],
            "span": [
              43,
              8,
              34
            ]
          },
          {
            "path": [
              4,
              0,
              2,
              5,
              6
            ],
            "span": [
              43,
              8,
              18
            ]
          },
          {
            "path": [
              4,
              0,
              2,
              5,
              1
            ],
            "span": [
              43,
              19,
              29
            ]
          },
          {
            "path": [
              4,
              0,
              2,
              5,
              3
            ],
            "span": [
              43,
              32,
              33
            ]
          },
          {
            "path": [
              4,
              0,
              2,
              6
            ],
            "span": [
              45,
              8,
              25
            ]
          },
          {
            "path": [
              4,
              0,
              2,
              6,
              6
            ],
            "span": [
              45,
              8,
              15
            ]
          },
          {
            "path": [
              4,
              0,
              2,
              6,
              1
            ],
            "span": [
              45,
              16,
              20
            ]
          },
          {
            "path": [
              4,
              0,
              2,
              6,
              3
            ],
            "span": [
              45,
              23,
              24
            ]
          },
          {
            "path": [
              4,
              0,
              2,
              7
            ],
            "span": [
              46,
              8,
              25
            ]
          },
          {
            "path": [
              4,
              0,
              2,
              7,
              6
            ],
            "span": [
              46,
              8,
              15
            ]
          },
          {
            "path": [
              4,
              0,
              2,
              7,
              1
            ],
            "span": [
              46,
              16,
              20
            ]
          },
          {
            "path": [
              4,
              0,
              2,
              7,
              3
            ],
            "span": [
              46,
              23,
              24
            ]
          },
          {
            "path": [
              4,
              0,
              2,
              8
            ],
            "span": [
              47,
              8,
              25
            ]
          },
          {
            "path": [
              4,
              0,
              2,
              8,
              6
            ],
            "span": [
              47,
              8,
              15
            ]
          },
          {
            "path": [
              4,
              0,
              2,
              8,
              1
            ],
            "span": [
              47,
              16,
              20
            ]
          },
          {
            "path": [
              4,
              0,
              2,
              8,
              3
            ],
            "span": [
              47,
              23,
              24
            ]
          },
          {
            "path": [
              4,
              0,
              2,
              9
            ],
            "span": [
              48,
              8,
              27
            ]
          },
          {
            "path": [
              4,
              0,
              2,
              9,
              6
            ],
            "span": [
              48,
              8,
              15
            ]
          },
          {
            "path": [
              4,
              0,
              2,
              9,
              1
            ],
            "span": [
              48,
              16,
              21
            ]
          },
          {
            "path": [
              4,
              0,
              2,
              9,
              3
            ],
            "span": [
              48,
              24,
              26
            ]
          },
          {
            "path": [
              4,
              0,
              2,
              10
            ],
            "span": [
              50,
              8,
              30
            ]
          },
          {
            "path": [
              4,
              0,
              2,
              10,
              6
            ],
            "span": [
              50,
              8,
              17
            ]
          },
          {
            "path": [
              4,
              0,
              2,
              10,
              1
            ],
            "span": [
              50,
              18,
              24
            ]
          },
          {
            "path": [
              4,
              0,
              2,
              10,
              3
            ],
            "span": [
              50,
              27,
              29
            ]
          },
          {
            "path": [
              4,
              0,
              2,
              11
            ],
            "span": [
              51,
              8,
              34
            ]
          },
          {
            "path": [
              4,
              0,
              2,
              11,
              6
            ],
            "span": [
              51,
              8,
              17
            ]
          },
          {
            "path": [
              4,
              0,
              2,
              11,
              1
            ],
            "span": [
              51,
              18,
              28
            ]
          },
          {
            "path": [
              4,
              0,
              2,
              11,
              3
            ],
            "span": [
              51,
              31,
              33
            ]
          },
          {
            "path": [
              4,
              0,
              2,
              12
            ],
            "span": [
              53,
              8,
              35
            ]
          },
          {
            "path": [
              4,
              0,
              2,
              12,
              6
            ],
            "span": [
              53,
              8,
              19
            ]
          },
          {
            "path": [
              4,
              0,
              2,
              12,
              1
            ],
            "span": [
              53,
              20,
              28
            ]
          },
          {
            "path": [
              4,
              0,
              2,
              12,
              3
            ],
            "span": [
              53,
              31,
              34
            ]
          },
          {
            "path": [
              4,
              0,
              2,
              13
            ],
            "span": [
              54,
              8,
              35
            ]
          },
          {
            "path": [
              4,
              0,
              2,
              13,
              6
            ],
            "span": [
              54,
              8,
              19
            ]
          },
          {
            "path": [
              4,
              0,
              2,
              13,
              1
            ],
            "span": [
              54,
              20,
              28
            ]
          },
          {
            "path": [
              4,
              0,
              2,
              13,
              3
            ],
            "span": [
              54,
              31,
              34
            ]
          },
          {
            "path": [
              4,
              1
            ],
            "span": [
              58,
              0,
              62,
              1
            ]
          },
          {
            "path": [
              4,
              1,
              1
            ],
            "span": [
              58,
              8,
              16
            ]
          },
          {
            "path": [
              4,
              1,
              2,
              0
            ],
            "span": [
              59,
              4,
              24
            ]
          },
          {
            "path": [
              4,
              1,
              2,
              0,
              5
            ],
            "span": [
              59,
              4,
              10
            ]
          },
          {
            "path": [
              4,
              1,
              2,
              0,
              1
            ],
            "span": [
              59,
              11,
              19
            ]
          },
          {
            "path": [
              4,
              1,
              2,
              0,
              3
            ],
            "span": [
              59,
              22,
              23
            ]
          },
          {
            "path": [
              4,
              1,
              2,
              1
            ],
            "span": [
              60,
              4,
              35
            ]
          },
          {
            "path": [
              4,
              1,
              2,
              1,
              5
            ],
            "span": [
              60,
              4,
              10
            ]
          },
          {
            "path": [
              4,
              1,
              2,
              1,
              1
            ],
            "span": [
              60,
              11,
              30
            ]
          },
          {
            "path": [
              4,
              1,
              2,
              1,
              3
            ],
            "span": [
              60,
              33,
              34
            ]
          },
          {
            "path": [
              4,
              1,
              2,
              2
            ],
            "span": [
              61,
              4,
              20
            ]
          },
          {
            "path": [
              4,
              1,
              2,
              2,
              5
            ],
            "span": [
              61,
              4,
              9
            ]
          },
          {
            "path": [
              4,
              1,
              2,
              2,
              1
            ],
            "span": [
              61,
              10,
              15
            ]
          },
          {
            "path": [
              4,
              1,
              2,
              2,
              3
            ],
            "span": [
              61,
              18,
              19
            ]
          },
          {
            "path": [
              4,
              2
            ],
            "span": [
              64,
              0,
              66,
              1
            ]
          },
          {
            "path": [
              4,
              2,
              1
            ],
            "span": [
              64,
              8,
              18
            ]
          },
          {
            "path": [
              4,
              2,
              2,
              0
            ],
            "span": [
              65,
              4,
              24
            ]
          },
          {
            "path": [
              4,
              2,
              2,
              0,
              5
            ],
            "span": [
              65,
              4,
              10
            ]
          },
          {
            "path": [
              4,
              2,
              2,
              0,
              1
            ],
            "span": [
              65,
              11,
              19
            ]
          },
          {
            "path": [
              4,
              2,
              2,
              0,
              3
            ],
            "span": [
              65,
              22,
              23
            ]
          },
          {
            "path": [
              4,
              3
            ],
            "span": [
              68,
              0,
              73,
              1
            ]
          },
          {
            "path": [
              4,
              3,
              1
            ],
            "span": [
              68,
              8,
              14
            ]
          },
          {
            "path": [
              4,
              3,
              2,
              0
            ],
            "span": [
              69,
              4,
              24
            ]
          },
          {
            "path": [
              4,
              3,
              2,
              0,
              5
            ],
            "span": [
              69,
              4,
              10
            ]
          },
          {
            "path": [
              4,
              3,
              2,
              0,
              1
            ],
            "span": [
              69,
              11,
              19
            ]
          },
          {
            "path": [
              4,
              3,
              2,
              0,
              3
            ],
            "span": [
              69,
              22,
              23
            ]
          },
          {
            "path": [
              4,
              3,
              2,
              1
            ],
            "span": [
              70,
              4,
              22
            ]
          },
          {
            "path": [
              4,
              3,
              2,
              1,
              5
            ],
            "span": [
              70,
              4,
              8
            ]
          },
          {
            "path": [
              4,
              3,
              2,
              1,
              1
            ],
            "span": [
              70,
              9,
              17
            ]
          },
          {
            "path": [
              4,
              3,
              2,
              1,
              3
            ],
            "span": [
              70,
              20,
              21
            ]
          },
          {
            "path": [
              4,
              3,
              2,
              2
            ],
            "span": [
              71,
              4,
              23
            ]
          },
          {
            "path": [
              4,
              3,
              2,
              2,
              5
            ],
            "span": [
              71,
              4,
              9
            ]
          },
          {
            "path": [
              4,
              3,
              2,
              2,
              1
            ],
            "span": [
              71,
              10,
              18
            ]
          },
          {
            "path": [
              4,
              3,
              2,
              2,
              3
            ],
            "span": [
              71,
              21,
              22
            ]
          },
          {
            "path": [
              4,
              3,
              2,
              3
            ],
            "span": [
              72,
              4,
              22
            ]
          },
          {
            "path": [
              4,
              3,
              2,
              3,
              5
            ],
            "span": [
              72,
              4,
              10
            ]
          },
          {
            "path": [
              4,
              3,
              2,
              3,
              1
            ],
            "span": [
              72,
              11,
              17
            ]
          },
          {
            "path": [
              4,
              3,
              2,
              3,
              3
            ],
            "span": [
              72,
              20,
              21
            ]
          },
          {
            "path": [
              4,
              4
            ],
            "span": [
              75,
              0,
              80,
              1
            ]
          },
          {
            "path": [
              4,
              4,
              1
            ],
            "span": [
              75,
              8,
              16
            ]
          },
          {
            "path": [
              4,
              4,
              2,
              0
            ],
            "span": [
              76,
              4,
              24
            ]
          },
          {
            "path": [
              4,
              4,
              2,
              0,
              5
            ],
            "span": [
              76,
              4,
              10
            ]
          },
          {
            "path": [
              4,
              4,
              2,
              0,
              1
            ],
            "span": [
              76,
              11,
              19
            ]
          },
          {
            "path": [
              4,
              4,
              2,
              0,
              3
            ],
            "span": [
              76,
              22,
              23
            ]
          },
          {
            "path": [
              4,
              4,
              2,
              1
            ],
            "span": [
              77,
              4,
              22
            ]
          },
          {
            "path": [
              4,
              4,
              2,
              1,
              5
            ],
            "span": [
              77,
              4,
              8
            ]
          },
          {
            "path": [
              4,
              4,
              2,
              1,
              1
            ],
            "span": [
              77,
              9,
              17
            ]
          },
          {
            "path": [
              4,
              4,
              2,
              1,
              3
            ],
            "span": [
              77,
              20,
              21
            ]
          },
          {
            "path": [
              4,
              4,
              2,
              2
            ],
            "span": [
              78,
              4,
              22
            ]
          },
          {
            "path": [
              4,
              4,
              2,
              2,
              5
            ],
            "span": [
              78,
              4,
              9
            ]
          },
          {
            "path": [
              4,
              4,
              2,
              2,
              1
            ],
            "span": [
              78,
              10,
              17
            ]
          },
          {
            "path": [
              4,
              4,
              2,
              2,
              3
            ],
            "span": [
              78,
              20,
              21
            ]
          },
          {
            "path": [
              4,
              4,
              2,
              3
            ],
            "span": [
              79,
              4,
              22
            ]
          },
          {
            "path": [
              4,
              4,
              2,
              3,
              5
            ],
            "span": [
              79,
              4,
              10
            ]
          },
          {
            "path": [
              4,
              4,
              2,
              3,
              1
            ],
            "span": [
              79,
              11,
              17
            ]
          },
          {
            "path": [
              4,
              4,
              2,
              3,
              3
            ],
            "span": [
              79,
              20,
              21
            ]
          },
          {
            "path": [
              4,
              5
            ],
            "span": [
              82,
              0,
              89,
              1
            ]
          },
          {
            "path": [
              4,
              5,
              1
            ],
            "span": [
              82,
              8,
              18
            ]
          },
          {
            "path": [
              4,
              5,
              2,
              0
            ],
            "span": [
              83,
              4,
              24
            ]
          },
          {
            "path": [
              4,
              5,
              2,
              0,
              5
            ],
            "span": [
              83,
              4,
              10
            ]
          },
          {
            "path": [
              4,
              5,
              2,
              0,
              1
            ],
            "span": [
              83,
              11,
              19
            ]
          },
          {
            "path": [
              4,
              5,
              2,
              0,
              3
            ],
            "span": [
              83,
              22,
              23
            ]
          },
          {
            "path": [
              4,
              5,
              2,
              1
            ],
            "span": [
              84,
              4,
              22
            ]
          },
          {
            "path": [
              4,
              5,
              2,
              1,
              5
            ],
            "span": [
              84,
              4,
              9
            ]
          },
          {
            "path": [
              4,
              5,
              2,
              1,
              1
            ],
            "span": [
              84,
              10,
              17
            ]
          },
          {
            "path": [
              4,
              5,
              2,
              1,
              3
            ],
            "span": [
              84,
              20,
              21
            ]
          },
          {
            "path": [
              4,
              5,
              2,
              2
            ],
            "span": [
              85,
              4,
              24
            ]
          },
          {
            "path": [
              4,
              5,
              2,
              2,
              5
            ],
            "span": [
              85,
              4,
              9
            ]
          },
          {
            "path": [
              4,
              5,
              2,
              2,
              1
            ],
            "span": [
              85,
              10,
              19
            ]
          },
          {
            "path": [
              4,
              5,
              2,
              2,
              3
            ],
            "span": [
              85,
              22,
              23
            ]
          },
          {
            "path": [
              4,
              5,
              2,
              3
            ],
            "span": [
              86,
              4,
              24
            ]
          },
          {
            "path": [
              4,
              5,
              2,
              3,
              5
            ],
            "span": [
              86,
              4,
              9
            ]
          },
          {
            "path": [
              4,
              5,
              2,
              3,
              1
            ],
            "span": [
              86,
              10,
              19
            ]
          },
          {
            "path": [
              4,
              5,
              2,
              3,
              3
            ],
            "span": [
              86,
              22,
              23
            ]
          },
          {
            "path": [
              4,
              5,
              2,
              4
            ],
            "span": [
              88,
              4,
              34
            ]
          },
          {
            "path": [
              4,
              5,
              2,
              4,
              4
            ],
            "span": [
              88,
              4,
              12
            ]
          },
          {
            "path": [
              4,
              5,
              2,
              4,
              6
            ],
            "span": [
              88,
              13,
              23
            ]
          },
          {
            "path": [
              4,
              5,
              2,
              4,
              1
            ],
            "span": [
              88,
              24,
              29
            ]
          },
          {
            "path": [
              4,
              5,
              2,
              4,
              3
            ],
            "span": [
              88,
              32,
              33
            ]
          },
          {
            "path": [
              4,
              6
            ],
            "span": [
              91,
              0,
              95,
              1
            ]
          },
          {
            "path": [
              4,
              6,
              1
            ],
            "span": [
              91,
              8,
              18
            ]
          },
          {
            "path": [
              4,
              6,
              2,
              0
            ],
            "span": [
              92,
              4,
              22
            ]
          },
          {
            "path": [
              4,
              6,
              2,
              0,
              5
            ],
            "span": [
              92,
              4,
              10
            ]
          },
          {
            "path": [
              4,
              6,
              2,
              0,
              1
            ],
            "span": [
              92,
              11,
              17
            ]
          },
          {
            "path": [
              4,
              6,
              2,
              0,
              3
            ],
            "span": [
              92,
              20,
              21
            ]
          },
          {
            "path": [
              4,
              6,
              2,
              1
            ],
            "span": [
              93,
              4,
              22
            ]
          },
          {
            "path": [
              4,
              6,
              2,
              1,
              5
            ],
            "span": [
              93,
              4,
              9
            ]
          },
          {
            "path": [
              4,
              6,
              2,
              1,
              1
            ],
            "span": [
              93,
              10,
              17
            ]
          },
          {
            "path": [
              4,
              6,
              2,
              1,
              3
            ],
            "span": [
              93,
              20,
              21
            ]
          },
          {
            "path": [
              4,
              6,
              2,
              2
            ],
            "span": [
              94,
              4,
              23
            ]
          },
          {
            "path": [
              4,
              6,
              2,
              2,
              5
            ],
            "span": [
              94,
              4,
              9
            ]
          },
          {
            "path": [
              4,
              6,
              2,
              2,
              1
            ],
            "span": [
              94,
              10,
              18
            ]
          },
          {
            "path": [
              4,
              6,
              2,
              2,
              3
            ],
            "span": [
              94,
              21,
              22
            ]
          },
          {
            "path": [
              4,
              7
            ],
            "span": [
              97,
              0,
              101,
              1
            ]
          },
          {
            "path": [
              4,
              7,
              1
            ],
            "span": [
              97,
              8,
              12
            ]
          },
          {
            "path": [
              4,
              7,
              2,
              0
            ],
            "span": [
              98,
              4,
              19
            ]
          },
          {
            "path": [
              4,
              7,
              2,
              0,
              5
            ],
            "span": [
              98,
              4,
              9
            ]
          },
          {
            "path": [
              4,
              7,
              2,
              0,
              1
            ],
            "span": [
              98,
              10,
              14
            ]
          },
          {
            "path": [
              4,
              7,
              2,
              0,
              3
            ],
            "span": [
              98,
              17,
              18
            ]
          },
          {
            "path": [
              4,
              7,
              2,
              1
            ],
            "span": [
              99,
              4,
              19
            ]
          },
          {
            "path": [
              4,
              7,
              2,
              1,
              5
            ],
            "span": [
              99,
              4,
              9
            ]
          },
          {
            "path": [
              4,
              7,
              2,
              1,
              1
            ],
            "span": [
              99,
              10,
              14
            ]
          },
          {
            "path": [
              4,
              7,
              2,
              1,
              3
            ],
            "span": [
              99,
              17,
              18
            ]
          },
          {
            "path": [
              4,
              7,
              2,
              2
            ],
            "span": [
              100,
              4,
              23
            ]
          },
          {
            "path": [
              4,
              7,
              2,
              2,
              5
            ],
            "span": [
              100,
              4,
              10
            ]
          },
          {
            "path": [
              4,
              7,
              2,
              2,
              1
            ],
            "span": [
              100,
              11,
              18
            ]
          },
          {
            "path": [
              4,
              7,
              2,
              2,
              3
            ],
            "span": [
              100,
              21,
              22
            ]
          },
          {
            "path": [
              4,
              8
            ],
            "span": [
              103,
              0,
              105,
              1
            ]
          },
          {
            "path": [
              4,
              8,
              1
            ],
            "span": [
              103,
              8,
              15
            ]
          },
          {
            "path": [
              4,
              8,
              2,
              0
            ],
            "span": [
              104,
              4,
              28
            ]
          },
          {
            "path": [
              4,
              8,
              2,
              0,
              4
            ],
            "span": [
              104,
              4,
              12
            ]
          },
          {
            "path": [
              4,
              8,
              2,
              0,
              6
            ],
            "span": [
              104,
              13,
              17
            ]
          },
          {
            "path": [
              4,
              8,
              2,
              0,
              1
            ],
            "span": [
              104,
              18,
              23
            ]
          },
          {
            "path": [
              4,
              8,
              2,
              0,
              3
            ],
            "span": [
              104,
              26,
              27
            ]
          },
          {
            "path": [
              4,
              9
            ],
            "span": [
              107,
              0,
              109,
              1
            ]
          },
          {
            "path": [
              4,
              9,
              1
            ],
            "span": [
              107,
              8,
              19
            ]
          },
          {
            "path": [
              4,
              9,
              2,
              0
            ],
            "span": [
              108,
              4,
              20
            ]
          },
          {
            "path": [
              4,
              9,
              2,
              0,
              5
            ],
            "span": [
              108,
              4,
              10
            ]
          },
          {
            "path": [
              4,
              9,
              2,
              0,
              1
            ],
            "span": [
              108,
              11,
              15
            ]
          },
          {
            "path": [
              4,
              9,
              2,
              0,
              3
            ],
            "span": [
              108,
              18,
              19
            ]
          },
          {
            "path": [
              4,
              10
            ],
            "span": [
              111,
              0,
              116,
              1
            ]
          },
          {
            "path": [
              4,
              10,
              1
            ],
            "span": [
              111,
              8,
              19
            ]
          },
          {
            "path": [
              4,
              10,
              2,
              0
            ],
            "span": [
              112,
              4,
              25
            ]
          },
          {
            "path": [
              4,
              10,
              2,
              0,
              5
            ],
            "span": [
              112,
              4,
              9
            ]
          },
          {
            "path": [
              4,
              10,
              2,
              0,
              1
            ],
            "span": [
              112,
              10,
              20
            ]
          },
          {
            "path": [
              4,
              10,
              2,
              0,
              3
            ],
            "span": [
              112,
              23,
              24
            ]
          },
          {
            "path": [
              4,
              10,
              2,
              1
            ],
            "span": [
              113,
              4,
              25
            ]
          },
          {
            "path": [
              4,
              10,
              2,
              1,
              5
            ],
            "span": [
              113,
              4,
              10
            ]
          },
          {
            "path": [
              4,
              10,
              2,
              1,
              1
            ],
            "span": [
              113,
              11,
              20
            ]
          },
          {
            "path": [
              4,
              10,
              2,
              1,
              3
            ],
            "span": [
              113,
              23,
              24
            ]
          },
          {
            "path": [
              4,
              10,
              2,
              2
            ],
            "span": [
              114,
              4,
              20
            ]
          },
          {
            "path": [
              4,
              10,
              2,
              2,
              5
            ],
            "span": [
              114,
              4,
              10
            ]
          },
          {
            "path": [
              4,
              10,
              2,
              2,
              1
            ],
            "span": [
              114,
              11,
              15
            ]
          },
          {
            "path": [
              4,
              10,
              2,
              2,
              3
            ],
            "span": [
              114,
              18,
              19
            ]
          },
          {
            "path": [
              4,
              10,
              2,
              3
            ],
            "span": [
              115,
              4,
              24
            ]
          },
          {
            "path": [
              4,
              10,
              2,
              3,
              5
            ],
            "span": [
              115,
              4,
              9
            ]
          },
          {
            "path": [
              4,
              10,
              2,
              3,
              1
            ],
            "span": [
              115,
              10,
              19
            ]
          },
          {
            "path": [
              4,
              10,
              2,
              3,
              3
            ],
            "span": [
              115,
              22,
              23
            ]
          },
          {
            "path": [
              5,
              1
            ],
            "span": [
              118,
              0,
              126,
              1
            ]
          },
          {
            "path": [
              5,
              1,
              1
            ],
            "span": [
              118,
              5,
              15
            ]
          },
          {
            "path": [
              5,
              1,
              2,
              0
            ],
            "span": [
              119,
              4,
              16
            ]
          },
          {
            "path": [
              5,
              1,
              2,
              0,
              1
            ],
            "span": [
              119,
              4,
              11
            ]
          },
          {
            "path": [
              5,
              1,
              2,
              0,
              2
            ],
            "span": [
              119,
              14,
              15
            ]
          },
          {
            "path": [
              5,
              1,
              2,
              1
            ],
            "span": [
              121,
              4,
              14
            ]
          },
          {
            "path": [
              5,
              1,
              2,
              1,
              1
            ],
            "span": [
              121,
              4,
              9
            ]
          },
          {
            "path": [
              5,
              1,
              2,
              1,
              2
            ],
            "span": [
              121,
              12,
              13
            ]
          },
          {
            "path": [
              5,
              1,
              2,
              2
            ],
            "span": [
              122,
              4,
              13
            ]
          },
          {
            "path": [
              5,
              1,
              2,
              2,
              1
            ],
            "span": [
              122,
              4,
              8
            ]
          },
          {
            "path": [
              5,
              1,
              2,
              2,
              2
            ],
            "span": [
              122,
              11,
              12
            ]
          },
          {
            "path": [
              5,
              1,
              2,
              3
            ],
            "span": [
              123,
              4,
              12
            ]
          },
          {
            "path": [
              5,
              1,
              2,
              3,
              1
            ],
            "span": [
              123,
              4,
              7
            ]
          },
          {
            "path": [
              5,
              1,
              2,
              3,
              2
            ],
            "span": [
              123,
              10,
              11
            ]
          },
          {
            "path": [
              5,
              1,
              2,
              4
            ],
            "span": [
              124,
              4,
              14
            ]
          },
          {
            "path": [
              5,
              1,
              2,
              4,
              1
            ],
            "span": [
              124,
              4,
              9
            ]
          },
          {
            "path": [
              5,
              1,
              2,
              4,
              2
            ],
            "span": [
              124,
              12,
              13
            ]
          },
          {
            "path": [
              5,
              1,
              2,
              5
            ],
            "span": [
              125,
              4,
              15
            ]
          },
          {
            "path": [
              5,
              1,
              2,
              5,
              1
            ],
            "span": [
              125,
              4,
              10
            ]
          },
          {
            "path": [
              5,
              1,
              2,
              5,
              2
            ],
            "span": [
              125,
              13,
              14
            ]
          },
          {
            "path": [
              4,
              11
            ],
            "span": [
              128,
              0,
              132,
              1
            ]
          },
          {
            "path": [
              4,
              11,
              1
            ],
            "span": [
              128,
              8,
              17
            ]
          },
          {
            "path": [
              4,
              11,
              2,
              0
            ],
            "span": [
              129,
              4,
              24
            ]
          },
          {
            "path": [
              4,
              11,
              2,
              0,
              6
            ],
            "span": [
              129,
              4,
              14
            ]
          },
          {
            "path": [
              4,
              11,
              2,
              0,
              1
            ],
            "span": [
              129,
              15,
              19
            ]
          },
          {
            "path": [
              4,
              11,
              2,
              0,
              3
            ],
            "span": [
              129,
              22,
              23
            ]
          },
          {
            "path": [
              4,
              11,
              2,
              1
            ],
            "span": [
              130,
              4,
              20
            ]
          },
          {
            "path": [
              4,
              11,
              2,
              1,
              5
            ],
            "span": [
              130,
              4,
              9
            ]
          },
          {
            "path": [
              4,
              11,
              2,
              1,
              1
            ],
            "span": [
              130,
              10,
              15
            ]
          },
          {
            "path": [
              4,
              11,
              2,
              1,
              3
            ],
            "span": [
              130,
              18,
              19
            ]
          },
          {
            "path": [
              4,
              11,
              2,
              2
            ],
            "span": [
              131,
              4,
              20
            ]
          },
          {
            "path": [
              4,
              11,
              2,
              2,
              5
            ],
            "span": [
              131,
              4,
              9
            ]
          },
          {
            "path": [
              4,
              11,
              2,
              2,
              1
            ],
            "span": [
              131,
              10,
              15
            ]
          },
          {
            "path": [
              4,
              11,
              2,
              2,
              3
            ],
            "span": [
              131,
              18,
              19
            ]
          },
          {
            "path": [
              4,
              12
            ],
            "span": [
              134,
              0,
              138,
              1
            ]
          },
          {
            "path": [
              4,
              12,
              1
            ],
            "span": [
              134,
              8,
              17
            ]
          },
          {
            "path": [
              4,
              12,
              2,
              0
            ],
            "span": [
              135,
              4,
              16
            ]
          },
          {
            "path": [
              4,
              12,
              2,
              0,
              5
            ],
            "span": [
              135,
              4,
              8
            ]
          },
          {
            "path": [
              4,
              12,
              2,
              0,
              1
            ],
            "span": [
              135,
              9,
              11
            ]
          },
          {
            "path": [
              4,
              12,
              2,
              0,
              3
            ],
            "span": [
              135,
              14,
              15
            ]
          },
          {
            "path": [
              4,
              12,
              2,
              1
            ],
            "span": [
              136,
              4,
              21
            ]
          },
          {
            "path": [
              4,
              12,
              2,
              1,
              5
            ],
            "span": [
              136,
              4,
              10
            ]
          },
          {
            "path": [
              4,
              12,
              2,
              1,
              1
            ],
            "span": [
              136,
              11,
              16
            ]
          },
          {
            "path": [
              4,
              12,
              2,
              1,
              3
            ],
            "span": [
              136,
              19,
              20
            ]
          },
          {
            "path": [
              4,
              12,
              2,
              2
            ],
            "span": [
              137,
              4,
              20
            ]
          },
          {
            "path": [
              4,
              12,
              2,
              2,
              5
            ],
            "span": [
              137,
              4,
              9
            ]
          },
          {
            "path": [
              4,
              12,
              2,
              2,
              1
            ],
            "span": [
              137,
              10,
              15
            ]
          },
          {
            "path": [
              4,
              12,
              2,
              2,
              3
            ],
            "span": [
              137,
              18,
              19
            ]
          }
        ]
      },
      "syntax": "proto3"
    }
  ],
  "compiler_version": {
    "major": 3,
    "minor": 11,
    "patch": 4,
    "suffix": ""
  }
}